torch_accelerator/__init__.py
torch_accelerator-0.0.1.dist-info/LICENSE
torch_accelerator-0.0.1.dist-info/METADATA
torch_accelerator-0.0.1.dist-info/WHEEL
torch_accelerator-0.0.1.dist-info/top_level.txt
torch_accelerator-0.0.1.dist-info/RECORD
