Metadata-Version: 2.1
Name: torch-accelerator
Version: 0.0.1
Summary: Easy to use package for accelerate your pytorch model inference
Home-page: https://github.com/Sid1057/TorchAccelerator
Author: sid1057
Author-email: ivanov.dale@gmail.com
License: UNKNOWN
Project-URL: Bug Tracker, https://github.com/Sid1057/TorchAccelerator/issues
Platform: UNKNOWN
Classifier: Programming Language :: Python :: 3
Classifier: License :: OSI Approved :: MIT License
Classifier: Operating System :: OS Independent
Requires-Python: >=3.6
